yta_editor_nodes/__init__.py
yta_editor_nodes/abstract.py
yta_editor_nodes/blender/__init__.py
yta_editor_nodes/blender/add.py
yta_editor_nodes/blender/alpha.py
yta_editor_nodes/blender/base.py
yta_editor_nodes/blender/mix.py
yta_editor_nodes/complex/__init__.py
yta_editor_nodes/complex/base.py
yta_editor_nodes/complex/display_over_at.py
yta_editor_nodes/compositor/__init__.py
yta_editor_nodes/compositor/base.py
yta_editor_nodes/compositor/displacement_with_rotation.py
yta_editor_nodes/old_opengl/__init__.py
yta_editor_nodes/old_opengl/effects.py
yta_editor_nodes/old_opengl/new_nodes.py
yta_editor_nodes/processor/__init__.py
yta_editor_nodes/processor/base.py
yta_editor_nodes/processor/black_and_white.py
yta_editor_nodes/processor/brightness.py
yta_editor_nodes/processor/color_contrast.py
yta_editor_nodes/processor/selection_mask.py
yta_editor_nodes/processor/video/__init__.py
yta_editor_nodes/processor/video/base.py
yta_editor_nodes/processor/video/breathing_frame.py
yta_editor_nodes/processor/video/transitions/__init__.py
yta_editor_nodes/processor/video/transitions/alphapedia_mask.py
yta_editor_nodes/processor/video/transitions/bars_falling.py
yta_editor_nodes/processor/video/transitions/base.py
yta_editor_nodes/processor/video/transitions/circle_closing.py
yta_editor_nodes/processor/video/transitions/circle_opening.py
yta_editor_nodes/processor/video/transitions/crossfade.py
yta_editor_nodes/processor/video/transitions/distorted_crossfade.py
yta_editor_nodes/processor/video/transitions/slide.py
yta_editor_nodes/processor/video/waving_frame.py
yta_editor_nodes/timed.py
yta_editor_nodes/timeline/__init__.py
yta_editor_nodes/timeline/abstract.py
yta_editor_nodes/timeline/layer/__init__.py
yta_editor_nodes/timeline/layer/abstract.py
yta_editor_nodes/timeline/parallel/__init__.py
yta_editor_nodes/timeline/parallel/abstract.py
yta_editor_nodes/timeline/serial/__init__.py
yta_editor_nodes/timeline/utils.py
yta_editor_nodes/utils.py
yta_editor_nodes-0.1.4.dist-info/licenses/LICENSE
yta_editor_nodes-0.1.4.dist-info/METADATA
yta_editor_nodes-0.1.4.dist-info/WHEEL
yta_editor_nodes-0.1.4.dist-info/RECORD
