Metadata-Version: 2.4
Name: yta-editor-nodes
Version: 0.1.4
Summary: Youtube Autonomous Main Editor Nodes module
License-File: LICENSE
Author: danialcala94
Author-email: danielalcalavalera@gmail.com
Requires-Python: ==3.9
Classifier: Programming Language :: Python :: 3
Classifier: Programming Language :: Python :: 3.9
Requires-Dist: yta_editor_nodes_cpu (>=0.0.1,<1.0.0)
Requires-Dist: yta_editor_nodes_gpu (>=0.0.1,<1.0.0)
Requires-Dist: yta_editor_parameters (>=0.0.1,<1.0.0)
Requires-Dist: yta_math_easings (>=0.0.1,<1.0.0)
Requires-Dist: yta_programming (>=0.0.1,<1.0.0)
Requires-Dist: yta_validation (>=0.0.1,<1.0.0)
